{"ALEUTIAN ISLANDS": ["ALEUTIANS EAST BOROUGH", "ALEUTIANS WEST CENSUS AREA"], "ANCHORAGE DISTRICT": ["ANCHORAGE BOROUGH"], "BETHEL DISTRICT & KUSKOKWIM DISTRICT": ["BETHEL CENSUS AREA"], "BRISTOL BAY DIVISION": ["BRISTOL BAY BOROUGH"], "BRISTOL BAY BOROUGH (IN PART)": ["DILLINGHAM CENSUS AREA"], "DILLINGHAM CENSUS AREA (IN PART)": ["LAKE AND PENINSULA BOROUGH"], "FAIRBANKS DISTRICT": ["FAIRBANKS NORTH STAR BOROUGH"], "SOUTHEAST FAIRBANKS DISTRICT": ["SOUTHEAST FAIRBANKS CENSUS AREA"], "JUNEAU DISTRICT": ["JUNEAU BOROUGH"], "KENAI-COOK INLET DISTRICT & SEWARD DISTRICT": ["KENAI PENINSULA BOROUGH"], "KETCHIKAN DISTRICT": ["KETCHIKAN GATEWAY BOROUGH", "KODIAK ISLAND BOROUGH"], "PALMER-WASILLA DISTRICT": ["MATANUSKA-SUSITNA BOROUGH"], "NOME DISTRICT": ["NOME CENSUS AREA"], "BARROW DISTRICT": ["NORTH SLOPE BOROUGH"], "KOBUK CENSUS AREA": ["NORTHWEST ARCTIC BOROUGH"], "OUTER KETCHIKAN DISTRICT & PRINCE OF WALES DISTRICT": ["PRINCE OF WALES-OUTER KETCHIKAN CENSUS AREA"], "SITKA DISTRICT": ["SITKA BOROUGH"], "SKAGWAY-YAKUTAT-ANGOON CENSUS AREA": ["SKAGWAY-HOONAH-ANGOON CENSUS AREA"], "SKAGWAY-YAKUTAT-ANGOON CENSUS AREA (IN PART)": ["YAKUTAT CENSUS AREA"], "CORDOVA-MCCARTHY DISTRICT & VALDEZ-CHITINA-WHITTIER DISTRICT": ["VALDEZ-CORDOVA CENSUS AREA"], "WADE HAMPTON DISTRICT": ["WADE HAMPTON CENSUS AREA"], "WRANGELL DISTRICT": ["WRANGELL-PETERSBURG CENSUS AREA"], "UPPER YUKON DISTRICT & YUKON-KOYUKUK DISTRICT": ["YUKON-KOYUKUK CENSUS AREA"], "YUKON-KOYUKUK CENSUS AREA (IN PART)": ["DENALI BOROUGH"], "YUMA COUNTY": ["YUMA COUNTY"], "YUMA COUNTY (IN PART)": ["LA PAZ COUNTY"], "ADAMS, BOULDER, JEFFERSON, AND WELD COUNTIES": ["ADAMS, BOULDER, JEFFERSON, AND WELD COUNTIES"], "ADAMS, BOULDER, JEFFERSON, AND WELD COUNTIES (IN PART)": ["BROOMFIELD COUNTY"], "DADE COUNTY": ["MIAMI-DADE COUNTY"], "MAUI COUNTY": ["MAUI COUNTY"], "MAUI COUNTY (IN PART)": ["KALAWAO COUNTY"], "VALENCIA COUNTY": ["VALENCIA COUNTY"], "VALENCIA COUNTY (IN PART)": ["CIBOLA COUNTY"], "BRONX BOROUGH": ["BRONX COUNTY"], "BROOKLYN BOROUGH": ["KINGS COUNTY"], "MANHATTAN BOROUGH": ["NEW YORK COUNTY"], "QUEENS BOROUGH": ["QUEENS COUNTY"], "STATEN ISLAND BOROUGH": ["RICHMOND COUNTY"], "WASHABAUGH COUNTY": ["JACKSON COUNTY"], "ALLEGHANY COUNTY": ["ALLEGHANY COUNTY"], "AUGUSTA COUNTY": ["AUGUSTA COUNTY"], "AUGUSTA COUNTY (IN PART)": ["WAYNESBORO CITY"], "CHESAPEAKE CITY": ["CHESAPEAKE CITY"], "CHESAPEAKE CITY (IN PART)": ["PORTSMOUTH CITY", "VIRGINIA BEACH CITY"], "FREDERICK COUNTY": ["FREDERICK COUNTY"], "FREDERICK COUNTY (IN PART)": ["WINCHESTER CITY"], "HALIFAX COUNTY": ["HALIFAX COUNTY"], "JAMES CITY COUNTY": ["JAMES CITY COUNTY"], "JAMES CITY COUNTY (IN PART)": ["WILLIAMSBURG CITY"], "PRINCE WILLIAM COUNTY": ["PRINCE WILLIAM COUNTY"], "PRINCE WILLIAM COUNTY (IN PART)": ["MANASSAS CITY", "MANASSAS PARK CITY"], "SUFFOLK CITY": ["SUFFOLK CITY"], "NANSEMOND COUNTY": ["SUFFOLK CITY"], "NANSEMOND CITY": ["SUFFOLK CITY"], "YORK COUNTY": ["YORK COUNTY"], "YORK COUNTY (IN PART)": ["POQUOSON CITY"]}